ft/__init__.py
ft/api.py
ft/base.py
ft_api-1.0.1.dist-info/METADATA
ft_api-1.0.1.dist-info/WHEEL
ft_api-1.0.1.dist-info/top_level.txt
ft_api-1.0.1.dist-info/RECORD
