Metadata-Version: 2.1
Name: ft-api
Version: 1.0.1
Summary: api for 42
Home-page: http://github.com/YutaUra/42-api
Author: Yuta Ura
Author-email: yuuta3594@outlook.jp
License: MIT
Requires-Dist: bleach (==3.1.0)
Requires-Dist: certifi (==2019.11.28)
Requires-Dist: chardet (==3.0.4)
Requires-Dist: docutils (==0.16)
Requires-Dist: idna (==2.8)
Requires-Dist: importlib-metadata (==1.4.0)
Requires-Dist: keyring (==21.1.0)
Requires-Dist: more-itertools (==8.1.0)
Requires-Dist: pkginfo (==1.5.0.1)
Requires-Dist: Pygments (==2.5.2)
Requires-Dist: pywin32-ctypes (==0.2.0)
Requires-Dist: readme-renderer (==24.0)
Requires-Dist: requests (==2.22.0)
Requires-Dist: requests-toolbelt (==0.9.1)
Requires-Dist: six (==1.14.0)
Requires-Dist: tqdm (==4.41.1)
Requires-Dist: twine (==3.1.1)
Requires-Dist: urllib3 (==1.25.7)
Requires-Dist: webencodings (==0.5.1)
Requires-Dist: zipp (==1.0.0)
